pcons/__init__.py
pcons/__main__.py
pcons/cli.py
pcons/modules.py
pcons/builders/__init__.py
pcons/builders/compile.py
pcons/configure/__init__.py
pcons/configure/checks.py
pcons/configure/config.py
pcons/configure/platform.py
pcons/contrib/__init__.py
pcons/contrib/bundle.py
pcons/contrib/platform.py
pcons/contrib/installers/__init__.py
pcons/contrib/installers/_helpers.py
pcons/contrib/installers/macos.py
pcons/contrib/installers/windows.py
pcons/contrib/windows/__init__.py
pcons/contrib/windows/manifest.py
pcons/core/__init__.py
pcons/core/builder.py
pcons/core/builder_registry.py
pcons/core/debug.py
pcons/core/environment.py
pcons/core/errors.py
pcons/core/flags.py
pcons/core/graph.py
pcons/core/node.py
pcons/core/paths.py
pcons/core/project.py
pcons/core/requirements.py
pcons/core/resolver.py
pcons/core/subst.py
pcons/core/target.py
pcons/core/toolconfig.py
pcons/core/types.py
pcons/generators/__init__.py
pcons/generators/compile_commands.py
pcons/generators/dot.py
pcons/generators/generator.py
pcons/generators/makefile.py
pcons/generators/mermaid.py
pcons/generators/ninja.py
pcons/generators/xcode.py
pcons/packages/__init__.py
pcons/packages/description.py
pcons/packages/imported.py
pcons/packages/fetch/__init__.py
pcons/packages/fetch/cli.py
pcons/packages/finders/__init__.py
pcons/packages/finders/base.py
pcons/packages/finders/conan.py
pcons/packages/finders/pkgconfig.py
pcons/packages/finders/system.py
pcons/toolchains/__init__.py
pcons/toolchains/_msvc_compat.py
pcons/toolchains/build_context.py
pcons/toolchains/clang_cl.py
pcons/toolchains/cuda.py
pcons/toolchains/cython.py
pcons/toolchains/gcc.py
pcons/toolchains/llvm.py
pcons/toolchains/msvc.py
pcons/toolchains/presets.py
pcons/toolchains/unix.py
pcons/tools/__init__.py
pcons/tools/archive.py
pcons/tools/archive_context.py
pcons/tools/cuda.py
pcons/tools/install.py
pcons/tools/tool.py
pcons/tools/toolchain.py
pcons/util/__init__.py
pcons/util/archive_helper.py
pcons/util/commands.py
pcons-0.7.1.dist-info/METADATA
pcons-0.7.1.dist-info/WHEEL
pcons-0.7.1.dist-info/entry_points.txt
pcons-0.7.1.dist-info/licenses/LICENSE
pcons-0.7.1.dist-info/RECORD
