Metadata-Version: 2.4
Name: pcons
Version: 0.7.1
Summary: A Python-based build system that generates Ninja files
Project-URL: Homepage, https://github.com/DarkStarSystems/pcons
Project-URL: Repository, https://github.com/DarkStarSystems/pcons
Project-URL: Documentation, https://pcons.readthedocs.io/
Project-URL: Issues, https://github.com/DarkStarSystems/pcons/issues
Author-email: Gary Oberbrunner <garyo@oberbrunner.com>
License: MIT
License-File: LICENSE
Keywords: build,build-system,cmake,ninja,scons
Classifier: Development Status :: 2 - Pre-Alpha
Classifier: Environment :: Console
Classifier: Intended Audience :: Developers
Classifier: License :: OSI Approved :: MIT License
Classifier: Operating System :: OS Independent
Classifier: Programming Language :: Python :: 3
Classifier: Programming Language :: Python :: 3.11
Classifier: Programming Language :: Python :: 3.12
Classifier: Programming Language :: Python :: 3.13
Classifier: Topic :: Software Development :: Build Tools
Requires-Python: >=3.11
Requires-Dist: pbxproj>=3.0.0
Requires-Dist: tomli-w>=1.0
Requires-Dist: tomli>=2.0; python_version < '3.11'
Provides-Extra: dev
Requires-Dist: mypy>=1.0; extra == 'dev'
Requires-Dist: pytest-cov>=4.0; extra == 'dev'
Requires-Dist: pytest>=8.0; extra == 'dev'
Requires-Dist: ruff>=0.4; extra == 'dev'
Provides-Extra: docs
Requires-Dist: mkdocs-material>=9.0; extra == 'docs'
Requires-Dist: mkdocs>=1.5; extra == 'docs'
